{"NA": {"5.11": {"NORMAL_5X5": {"NO_RANK": {"matchesCounted": 174, "averageTotalDamageDealt": 127839, "averageMagicDamageDealtToChampions": 19512, "matchesWon": 82, "averageGoldPerMin": 327.6364675457453, "averageKda": 2.964284117580265, "averageCsAt10": 4.371839080459768, "averageCsPerMin": 4.463551756160618, "winRate": "47.13", "averageMagicDamageDealt": 111315, "averageTotalDamageDealtToChampions": 21562, "mostCommonItems": {"3174": {"buyCount": 82, "averageTimeBought": 1071709, "buyPercentage": 47.953216374269005, "isApItem": true, "id": 3174}, "3020": {"buyCount": 142, "averageTimeBought": 1101439, "buyPercentage": 81.60919540229885, "isApItem": false, "id": 3020}, "3089": {"buyCount": 71, "averageTimeBought": 1698099, "buyPercentage": 42.51497005988024, "isApItem": true, "id": 3089}, "3157": {"buyCount": 49, "averageTimeBought": 1518476, "buyPercentage": 28.994082840236686, "isApItem": true, "id": 3157}, "3165": {"buyCount": 74, "averageTimeBought": 828541, "buyPercentage": 42.5287356321839, "isApItem": true, "id": 3165}, "3285": {"buyCount": 80, "averageTimeBought": 1250367, "buyPercentage": 45.97701149425287, "isApItem": true, "id": 3285}}}}, "RANKED_SOLO": {"PLATINUM": {"matchesCounted": 26, "averageTotalDamageDealt": 155385, "averageMagicDamageDealtToChampions": 20278, "matchesWon": 10, "averageGoldPerMin": 345.99531520818795, "averageKda": 2.5617521367521365, "averageCsAt10": 5.5807692307692305, "averageCsPerMin": 5.906099657420304, "winRate": "38.46", "averageMagicDamageDealt": 140274, "averageTotalDamageDealtToChampions": 22025, "mostCommonItems": {"3174": {"buyCount": 16, "averageTimeBought": 718656, "buyPercentage": 61.53846153846154, "isApItem": true, "id": 3174}, "3020": {"buyCount": 25, "averageTimeBought": 1036962, "buyPercentage": 96.15384615384616, "isApItem": false, "id": 3020}, "3157": {"buyCount": 11, "averageTimeBought": 1290658, "buyPercentage": 44.0, "isApItem": true, "id": 3157}, "2041": {"buyCount": 1, "averageTimeBought": 207161, "buyPercentage": 50.0, "isApItem": false, "id": 2041}, "3165": {"buyCount": 9, "averageTimeBought": 762925, "buyPercentage": 50.0, "isApItem": true, "id": 3165}, "3285": {"buyCount": 14, "averageTimeBought": 1384944, "buyPercentage": 53.84615384615385, "isApItem": true, "id": 3285}}}, "GOLD": {"matchesCounted": 51, "averageTotalDamageDealt": 134553, "averageMagicDamageDealtToChampions": 20641, "matchesWon": 21, "averageGoldPerMin": 335.03274005593323, "averageKda": 2.5584966776143245, "averageCsAt10": 4.927450980392157, "averageCsPerMin": 5.000053532913732, "winRate": "41.18", "averageMagicDamageDealt": 119923, "averageTotalDamageDealtToChampions": 22592, "mostCommonItems": {"3174": {"buyCount": 27, "averageTimeBought": 1079348, "buyPercentage": 52.94117647058824, "isApItem": true, "id": 3174}, "3020": {"buyCount": 45, "averageTimeBought": 1123518, "buyPercentage": 88.23529411764706, "isApItem": false, "id": 3020}, "3089": {"buyCount": 22, "averageTimeBought": 1444898, "buyPercentage": 43.13725490196079, "isApItem": true, "id": 3089}, "3285": {"buyCount": 23, "averageTimeBought": 1196689, "buyPercentage": 46.0, "isApItem": true, "id": 3285}, "3165": {"buyCount": 20, "averageTimeBought": 670987, "buyPercentage": 40.816326530612244, "isApItem": true, "id": 3165}, "3135": {"buyCount": 15, "averageTimeBought": 2090042, "buyPercentage": 35.714285714285715, "isApItem": true, "id": 3135}}}, "SILVER": {"matchesCounted": 83, "averageTotalDamageDealt": 142118, "averageMagicDamageDealtToChampions": 23468, "matchesWon": 45, "averageGoldPerMin": 346.83961688796796, "averageKda": 3.7001804420479125, "averageCsAt10": 5.081927710843375, "averageCsPerMin": 4.9224787766370905, "winRate": "54.22", "averageMagicDamageDealt": 125323, "averageTotalDamageDealtToChampions": 25646, "mostCommonItems": {"3174": {"buyCount": 44, "averageTimeBought": 867893, "buyPercentage": 53.01204819277109, "isApItem": true, "id": 3174}, "3020": {"buyCount": 71, "averageTimeBought": 1122029, "buyPercentage": 85.54216867469879, "isApItem": false, "id": 3020}, "3089": {"buyCount": 43, "averageTimeBought": 1580311, "buyPercentage": 54.43037974683544, "isApItem": true, "id": 3089}, "3285": {"buyCount": 47, "averageTimeBought": 1388467, "buyPercentage": 56.62650602409639, "isApItem": true, "id": 3285}, "3070": {"buyCount": 1, "averageTimeBought": 142062, "buyPercentage": 50.0, "isApItem": false, "id": 3070}, "3135": {"buyCount": 27, "averageTimeBought": 1736195, "buyPercentage": 32.926829268292686, "isApItem": true, "id": 3135}}}, "BRONZE": {"matchesCounted": 29, "averageTotalDamageDealt": 163519, "averageMagicDamageDealtToChampions": 21693, "matchesWon": 18, "averageGoldPerMin": 333.71542273956567, "averageKda": 4.408380317001006, "averageCsAt10": 4.848275862068966, "averageCsPerMin": 4.804835975700731, "winRate": "62.07", "averageMagicDamageDealt": 141758, "averageTotalDamageDealtToChampions": 23950, "mostCommonItems": {"3041": {"buyCount": 1, "averageTimeBought": 731830, "buyPercentage": 50.0, "isApItem": false, "id": 3041}, "3174": {"buyCount": 17, "averageTimeBought": 1164232, "buyPercentage": 58.620689655172406, "isApItem": true, "id": 3174}, "3020": {"buyCount": 25, "averageTimeBought": 1430166, "buyPercentage": 89.28571428571429, "isApItem": false, "id": 3020}, "3089": {"buyCount": 17, "averageTimeBought": 1462253, "buyPercentage": 62.96296296296296, "isApItem": true, "id": 3089}, "2004": {"buyCount": 1, "averageTimeBought": 409062, "buyPercentage": 100.0, "isApItem": false, "id": 2004}, "3165": {"buyCount": 16, "averageTimeBought": 1130371, "buyPercentage": 55.172413793103445, "isApItem": true, "id": 3165}}}, "DIAMOND+": {"matchesCounted": 7, "averageTotalDamageDealt": 195397, "averageMagicDamageDealtToChampions": 28809, "matchesWon": 5, "averageGoldPerMin": 387.6046359436256, "averageKda": 3.8190476190476192, "averageCsAt10": 6.8428571428571425, "averageCsPerMin": 6.608206506155624, "winRate": "71.43", "averageMagicDamageDealt": 178160, "averageTotalDamageDealtToChampions": 31232, "mostCommonItems": {"1058": {"buyCount": 1, "averageTimeBought": 1064356, "buyPercentage": 100.0, "isApItem": true, "id": 1058}, "3020": {"buyCount": 7, "averageTimeBought": 865216, "buyPercentage": 100.0, "isApItem": false, "id": 3020}, "3089": {"buyCount": 3, "averageTimeBought": 1382644, "buyPercentage": 50.0, "isApItem": true, "id": 3089}, "3157": {"buyCount": 6, "averageTimeBought": 1639543, "buyPercentage": 85.71428571428571, "isApItem": true, "id": 3157}, "3165": {"buyCount": 4, "averageTimeBought": 698680, "buyPercentage": 57.14285714285714, "isApItem": true, "id": 3165}, "3135": {"buyCount": 5, "averageTimeBought": 1630343, "buyPercentage": 83.33333333333334, "isApItem": true, "id": 3135}}}}}, "5.14": {"NORMAL_5X5": {"NO_RANK": {"matchesCounted": 219, "averageTotalDamageDealt": 130765, "averageMagicDamageDealtToChampions": 19471, "matchesWon": 88, "averageGoldPerMin": 329.32216694597474, "averageKda": 2.6518681149247536, "averageCsAt10": 4.682648401826486, "averageCsPerMin": 4.749095358692012, "winRate": "40.18", "averageMagicDamageDealt": 114248, "averageTotalDamageDealtToChampions": 21429, "mostCommonItems": {"3174": {"buyCount": 110, "averageTimeBought": 965767, "buyPercentage": 50.45871559633027, "isApItem": true, "id": 3174}, "3020": {"buyCount": 178, "averageTimeBought": 1100550, "buyPercentage": 81.27853881278538, "isApItem": false, "id": 3020}, "3089": {"buyCount": 97, "averageTimeBought": 1698625, "buyPercentage": 44.29223744292237, "isApItem": true, "id": 3089}, "3157": {"buyCount": 75, "averageTimeBought": 1866832, "buyPercentage": 35.54502369668246, "isApItem": true, "id": 3157}, "3165": {"buyCount": 85, "averageTimeBought": 861199, "buyPercentage": 38.81278538812785, "isApItem": true, "id": 3165}, "3285": {"buyCount": 94, "averageTimeBought": 1460399, "buyPercentage": 42.922374429223744, "isApItem": true, "id": 3285}}}}, "RANKED_SOLO": {"PLATINUM": {"matchesCounted": 24, "averageTotalDamageDealt": 142707, "averageMagicDamageDealtToChampions": 20435, "matchesWon": 12, "averageGoldPerMin": 341.66305169478704, "averageKda": 2.477432058682059, "averageCsAt10": 5.866666666666666, "averageCsPerMin": 5.757790414974989, "winRate": "50.00", "averageMagicDamageDealt": 128788, "averageTotalDamageDealtToChampions": 22127, "mostCommonItems": {"1058": {"buyCount": 11, "averageTimeBought": 794111, "buyPercentage": 45.83333333333333, "isApItem": true, "id": 1058}, "3174": {"buyCount": 15, "averageTimeBought": 978343, "buyPercentage": 62.5, "isApItem": true, "id": 3174}, "3020": {"buyCount": 20, "averageTimeBought": 1126196, "buyPercentage": 95.23809523809523, "isApItem": false, "id": 3020}, "1026": {"buyCount": 10, "averageTimeBought": 929634, "buyPercentage": 45.45454545454545, "isApItem": true, "id": 1026}, "3089": {"buyCount": 12, "averageTimeBought": 1724160, "buyPercentage": 50.0, "isApItem": true, "id": 3089}, "3165": {"buyCount": 8, "averageTimeBought": 1348914, "buyPercentage": 40.0, "isApItem": true, "id": 3165}}}, "GOLD": {"matchesCounted": 61, "averageTotalDamageDealt": 137232, "averageMagicDamageDealtToChampions": 20135, "matchesWon": 21, "averageGoldPerMin": 340.8324617905223, "averageKda": 2.5047983437327694, "averageCsAt10": 5.255737704918032, "averageCsPerMin": 5.3594528677166275, "winRate": "34.43", "averageMagicDamageDealt": 122127, "averageTotalDamageDealtToChampions": 22045, "mostCommonItems": {"3174": {"buyCount": 41, "averageTimeBought": 806816, "buyPercentage": 67.21311475409836, "isApItem": true, "id": 3174}, "3020": {"buyCount": 51, "averageTimeBought": 1027283, "buyPercentage": 83.60655737704919, "isApItem": false, "id": 3020}, "3089": {"buyCount": 31, "averageTimeBought": 1426117, "buyPercentage": 50.81967213114754, "isApItem": true, "id": 3089}, "3285": {"buyCount": 27, "averageTimeBought": 1270739, "buyPercentage": 45.0, "isApItem": true, "id": 3285}, "1052": {"buyCount": 18, "averageTimeBought": 573263, "buyPercentage": 33.9622641509434, "isApItem": false, "id": 1052}, "3157": {"buyCount": 17, "averageTimeBought": 1479119, "buyPercentage": 29.82456140350877, "isApItem": true, "id": 3157}}}, "SILVER": {"matchesCounted": 97, "averageTotalDamageDealt": 152553, "averageMagicDamageDealtToChampions": 22713, "matchesWon": 49, "averageGoldPerMin": 342.522827634556, "averageKda": 3.729657157242057, "averageCsAt10": 4.954639175257735, "averageCsPerMin": 4.989670069893526, "winRate": "50.52", "averageMagicDamageDealt": 135986, "averageTotalDamageDealtToChampions": 24661, "mostCommonItems": {"1058": {"buyCount": 37, "averageTimeBought": 1112099, "buyPercentage": 39.361702127659576, "isApItem": true, "id": 1058}, "3174": {"buyCount": 49, "averageTimeBought": 805729, "buyPercentage": 51.041666666666664, "isApItem": true, "id": 3174}, "3020": {"buyCount": 88, "averageTimeBought": 1066651, "buyPercentage": 90.72164948453609, "isApItem": false, "id": 3020}, "3089": {"buyCount": 48, "averageTimeBought": 1703599, "buyPercentage": 52.74725274725275, "isApItem": true, "id": 3089}, "3285": {"buyCount": 44, "averageTimeBought": 1288028, "buyPercentage": 48.35164835164835, "isApItem": true, "id": 3285}, "3165": {"buyCount": 38, "averageTimeBought": 1040070, "buyPercentage": 39.175257731958766, "isApItem": true, "id": 3165}}}, "BRONZE": {"matchesCounted": 29, "averageTotalDamageDealt": 116141, "averageMagicDamageDealtToChampions": 18416, "matchesWon": 14, "averageGoldPerMin": 322.4397328432315, "averageKda": 3.1526447690240795, "averageCsAt10": 4.0103448275862075, "averageCsPerMin": 3.962816294045605, "winRate": "48.28", "averageMagicDamageDealt": 100516, "averageTotalDamageDealtToChampions": 20259, "mostCommonItems": {"3174": {"buyCount": 13, "averageTimeBought": 768520, "buyPercentage": 44.827586206896555, "isApItem": true, "id": 3174}, "3020": {"buyCount": 23, "averageTimeBought": 1207875, "buyPercentage": 82.14285714285714, "isApItem": false, "id": 3020}, "3089": {"buyCount": 11, "averageTimeBought": 1871443, "buyPercentage": 37.93103448275862, "isApItem": true, "id": 3089}, "3285": {"buyCount": 13, "averageTimeBought": 1644218, "buyPercentage": 48.148148148148145, "isApItem": true, "id": 3285}, "3165": {"buyCount": 12, "averageTimeBought": 851251, "buyPercentage": 42.857142857142854, "isApItem": true, "id": 3165}, "3135": {"buyCount": 5, "averageTimeBought": 1655010, "buyPercentage": 50.0, "isApItem": true, "id": 3135}}}, "DIAMOND+": {"matchesCounted": 15, "averageTotalDamageDealt": 155891, "averageMagicDamageDealtToChampions": 21558, "matchesWon": 7, "averageGoldPerMin": 375.1756194382143, "averageKda": 3.919259259259259, "averageCsAt10": 6.406666666666667, "averageCsPerMin": 6.656251502910521, "winRate": "46.67", "averageMagicDamageDealt": 139730, "averageTotalDamageDealtToChampions": 23264, "mostCommonItems": {"1001": {"buyCount": 1, "averageTimeBought": 497225, "buyPercentage": 50.0, "isApItem": false, "id": 1001}, "3116": {"buyCount": 2, "averageTimeBought": 1664100, "buyPercentage": 66.66666666666666, "isApItem": true, "id": 3116}, "3089": {"buyCount": 8, "averageTimeBought": 1054568, "buyPercentage": 57.14285714285714, "isApItem": true, "id": 3089}, "2003": {"buyCount": 1, "averageTimeBought": 35491, "buyPercentage": 50.0, "isApItem": false, "id": 2003}, "3165": {"buyCount": 7, "averageTimeBought": 493593, "buyPercentage": 53.84615384615385, "isApItem": true, "id": 3165}, "3020": {"buyCount": 13, "averageTimeBought": 957243, "buyPercentage": 86.66666666666667, "isApItem": false, "id": 3020}}}}}}}